discard/__init__.py
discard/categories_part2.py
discard/categories_part3.py
discard/categories_part4.py
discard/client.py
discard_api-1.0.0.dist-info/licenses/LICENSE
discard_api-1.0.0.dist-info/METADATA
discard_api-1.0.0.dist-info/WHEEL
discard_api-1.0.0.dist-info/top_level.txt
discard_api-1.0.0.dist-info/RECORD
